{"name":"inicio de sesion","id":"realizar-compra;inicio-de-sesion","testSteps":[{"number":1,"description":"Dado que el usuario esta en la pagina de inicio","duration":5946,"startTime":"2024-01-17T21:10:03.971-05:00[America/Bogota]","screenshots":[{"screenshot":"e1c42c7263a8dfc720e0b1d0268702f497c387cff27bfbbeb0c9daab02e375ed.png","timeStamp":1705543809917}],"result":"SUCCESS","precondition":false,"level":0,"children":[{"number":2,"description":"Abrir navegador","duration":5458,"startTime":"2024-01-17T21:10:04.435-05:00[America/Bogota]","screenshots":[{"screenshot":"e1c42c7263a8dfc720e0b1d0268702f497c387cff27bfbbeb0c9daab02e375ed.png","timeStamp":1705543809892}],"result":"SUCCESS","precondition":false,"level":1}]},{"number":3,"description":"Cuando da clic en la opcion iniciar sesion","duration":782,"startTime":"2024-01-17T21:10:09.919-05:00[America/Bogota]","screenshots":[{"screenshot":"5a059aee9316cda743051203fe169162b476795f9bc5dd39d40078f11f892951.png","timeStamp":1705543810701}],"result":"SUCCESS","precondition":false,"level":0,"children":[{"number":4,"description":"Click login","duration":738,"startTime":"2024-01-17T21:10:09.934-05:00[America/Bogota]","screenshots":[{"screenshot":"2a048eb9c3ac46a3bb8d82da554d1969c4145fa8366e5d0a5418c935257525b4.png","timeStamp":1705543810224},{"screenshot":"5a059aee9316cda743051203fe169162b476795f9bc5dd39d40078f11f892951.png","timeStamp":1705543810671}],"result":"SUCCESS","precondition":false,"level":1}]},{"number":5,"description":"Y escribe las cedenciales\r\n| usuario | clave |\r\n| Cinthia123 | Zeus123 |","duration":1616,"startTime":"2024-01-17T21:10:10.703-05:00[America/Bogota]","screenshots":[{"screenshot":"bdcb23fd05a9c7ad5f264659006ee43c606ac07ad6f27e691b76dea45311911e.png","timeStamp":1705543810992},{"screenshot":"43e397004cc1f6bff3761600bfcf07606ac6329a5023e9f5b1c910755926bdd6.png","timeStamp":1705543812319}],"result":"SUCCESS","precondition":false,"level":0,"children":[{"number":6,"description":"Ingresar user name: Cinthia123","duration":410,"startTime":"2024-01-17T21:10:11.017-05:00[America/Bogota]","screenshots":[{"screenshot":"bdcb23fd05a9c7ad5f264659006ee43c606ac07ad6f27e691b76dea45311911e.png","timeStamp":1705543811030},{"screenshot":"7c4b570e0a099de84f73dd7b753429b9d047a02e0a6fbed6b163a8b339d5d29f.png","timeStamp":1705543811426}],"result":"SUCCESS","precondition":false,"level":1},{"number":7,"description":"Ingresar password: Zeus123","duration":388,"startTime":"2024-01-17T21:10:11.428-05:00[America/Bogota]","screenshots":[{"screenshot":"7c4b570e0a099de84f73dd7b753429b9d047a02e0a6fbed6b163a8b339d5d29f.png","timeStamp":1705543811439},{"screenshot":"306f91d531eed32c6e4a5de6fa88a1138387e33f0d4483ffd5bc7cb6c32b28a8.png","timeStamp":1705543811816}],"result":"SUCCESS","precondition":false,"level":1},{"number":8,"description":"Click boton","duration":458,"startTime":"2024-01-17T21:10:11.817-05:00[America/Bogota]","screenshots":[{"screenshot":"306f91d531eed32c6e4a5de6fa88a1138387e33f0d4483ffd5bc7cb6c32b28a8.png","timeStamp":1705543811837},{"screenshot":"43e397004cc1f6bff3761600bfcf07606ac6329a5023e9f5b1c910755926bdd6.png","timeStamp":1705543812274}],"result":"SUCCESS","precondition":false,"level":1}]},{"number":9,"description":"Entonces el usuario podra ver el incio de la sesion exitasamente","duration":981,"startTime":"2024-01-17T21:10:12.321-05:00[America/Bogota]","screenshots":[{"screenshot":"cfa317386cdde8e0b082a29caa4a978c9dc5a1163864e6d8af66636a2a88bb0d.png","timeStamp":1705543812880},{"screenshot":"c8508a0753e0c69637e814e5764b85eeeb62acf62edc5ab7ccbcfed096030c8f.png","timeStamp":1705543813302}],"result":"SUCCESS","precondition":false,"level":0,"children":[{"number":10,"description":"Validar mensaje","duration":408,"startTime":"2024-01-17T21:10:12.883-05:00[America/Bogota]","screenshots":[{"screenshot":"cfa317386cdde8e0b082a29caa4a978c9dc5a1163864e6d8af66636a2a88bb0d.png","timeStamp":1705543812901},{"screenshot":"c8508a0753e0c69637e814e5764b85eeeb62acf62edc5ab7ccbcfed096030c8f.png","timeStamp":1705543813291}],"result":"SUCCESS","precondition":false,"level":1}]}],"userStory":{"id":"realizar-compra","storyName":"Realizar compra","path":"src/test/resources/compra.feature","type":"feature"},"featureTag":{"name":"Resources/Realizar compra","type":"feature","displayName":"Resources/Realizar compra"},"title":"inicio de sesion","backgroundTitle":"","backgroundDescription":"","startTime":"2024-01-17T21:10:03.861-05:00[America/Bogota]","duration":9441,"projectKey":"","sessionId":"3b8fe66ec5b35fcad9278806aba65e2c","driver":"chrome","isManualTestingUpToDate":false,"manual":false,"testSource":"Cucumber","result":"SUCCESS"}